{"bbox":[35.14832,31.82383,35.216417,31.9121],"features":[{"geometry":{"coordinates":[35.180150,31.832733],"type":"Point"},"properties":{"id":"m17b4ff.point"},"type":"Feature"},{"geometry":{"coordinates":[35.202000,31.912100],"type":"Point"},"properties":{"id":"m3b4f65.point"},"type":"Feature"},{"geometry":{"coordinates":[35.211700,31.908790],"type":"Point"},"properties":{"id":"m857981.point"},"type":"Feature"},{"geometry":{"coordinates":[35.187200,31.823830],"type":"Point"},"properties":{"id":"m8d753d.point"},"type":"Feature"},{"geometry":{"coordinates":[35.148320,31.833920],"type":"Point"},"properties":{"id":"mbcd830.point"},"type":"Feature"},{"geometry":{"coordinates":[35.214958,31.905142],"type":"Point"},"properties":{"id":"mebe332.point"},"type":"Feature"},{"geometry":{"coordinates":[35.183351,31.847451],"type":"Point"},"properties":{"id":"mf55105.point"},"type":"Feature"},{"geometry":{"coordinates":[35.216417,31.885136],"type":"Point"},"properties":{"id":"mfe37a0.point"},"type":"Feature"}],"metadata":{"name":"Beeroth"},"type":"FeatureCollection"}