{"bbox":[35.33033,31.8375,35.549444,32.38511],"features":[{"geometry":{"coordinates":[35.528210,32.381520],"type":"Point"},"properties":{"id":"m394045.point"},"type":"Feature"},{"geometry":{"coordinates":[35.397400,32.301810],"type":"Point"},"properties":{"id":"m3a5f36.point"},"type":"Feature"},{"geometry":{"coordinates":[35.549444,31.837500],"type":"Point"},"properties":{"id":"m65fe20.point"},"type":"Feature"},{"geometry":{"coordinates":[35.533530,32.385110],"type":"Point"},"properties":{"id":"mb1a2b2.point"},"type":"Feature"},{"geometry":{"coordinates":[35.330330,32.208710],"type":"Point"},"properties":{"id":"mde7fdc.point"},"type":"Feature"}],"metadata":{"name":"Aenon"},"type":"FeatureCollection"}