{"bbox":[34.997106,31.742265,35.065011,31.784708],"features":[{"geometry":{"coordinates":[34.997106,31.746288],"type":"Point"},"properties":{"id":"m26e38a.point"},"type":"Feature"},{"geometry":{"coordinates":[35.006303,31.784708],"type":"Point"},"properties":{"id":"m62a3cc.point"},"type":"Feature"},{"geometry":{"coordinates":[35.065011,31.742265],"type":"Point"},"properties":{"id":"ma365e4.point"},"type":"Feature"},{"geometry":{"coordinates":[35.010100,31.781097],"type":"Point"},"properties":{"id":"mda9727.point"},"type":"Feature"}],"metadata":{"name":"Ashnah 1"},"type":"FeatureCollection"}