{"bbox":[34.964918,31.880322,35.39736,32.36884],"features":[{"geometry":{"coordinates":[34.964918,31.880322],"type":"Point"},"properties":{"id":"m93008b.point"},"type":"Feature"},{"geometry":{"coordinates":[35.372500,32.354167],"type":"Point"},"properties":{"id":"me867d9.point"},"type":"Feature"},{"geometry":{"coordinates":[35.397360,32.368840],"type":"Point"},"properties":{"id":"mf2c1fd.point"},"type":"Feature"}],"metadata":{"name":"Bezek 2"},"type":"FeatureCollection"}