{"bbox":[34.93235,31.2328,34.9867,31.28619],"features":[{"geometry":{"coordinates":[34.986700,31.232800],"type":"Point"},"properties":{"id":"ma832c2.point"},"type":"Feature"},{"geometry":{"coordinates":[34.932350,31.286190],"type":"Point"},"properties":{"id":"mef1743.point"},"type":"Feature"}],"metadata":{"name":"Kabzeel"},"type":"FeatureCollection"}