{"bbox":[35.183351,31.823113,35.261111,31.8575],"features":[{"geometry":{"coordinates":[35.230718,31.823113],"type":"Point"},"properties":{"id":"m88819c.point"},"type":"Feature"},{"geometry":{"coordinates":[35.261111,31.857500],"type":"Point"},"properties":{"id":"mb1da27.point"},"type":"Feature"},{"geometry":{"coordinates":[35.183351,31.847451],"type":"Point"},"properties":{"id":"mf55105.point"},"type":"Feature"}],"metadata":{"name":"Geba 2"},"type":"FeatureCollection"}