{"bbox":[35.195465,31.832184,35.286111,31.978611],"features":[{"geometry":{"coordinates":[35.286111,31.978611],"type":"Point"},"properties":{"id":"m8136bc.point"},"type":"Feature"},{"geometry":{"coordinates":[35.195465,31.832184],"type":"Point"},"properties":{"id":"mc6365d.point"},"type":"Feature"}],"metadata":{"name":"Baal-hazor"},"type":"FeatureCollection"}