{"bbox":[35.09027,32.75885,35.310556,32.788056],"features":[{"geometry":{"coordinates":[35.310556,32.788056],"type":"Point"},"properties":{"id":"m42ac18.point"},"type":"Feature"},{"geometry":{"coordinates":[35.256944,32.785556],"type":"Point"},"properties":{"id":"mabe7ea.point"},"type":"Feature"},{"geometry":{"coordinates":[35.090270,32.758850],"type":"Point"},"properties":{"id":"md7c132.point"},"type":"Feature"}],"metadata":{"name":"Hannathon"},"type":"FeatureCollection"}