{"bbox":[35.209636,31.802528,35.236,31.89571],"features":[{"geometry":{"coordinates":[35.236000,31.847460],"type":"Point"},"properties":{"id":"m0431fc.point"},"type":"Feature"},{"geometry":{"coordinates":[35.209636,31.802528],"type":"Point"},"properties":{"id":"m934b82.point"},"type":"Feature"},{"geometry":{"coordinates":[35.218050,31.895710],"type":"Point"},"properties":{"id":"md02dab.point"},"type":"Feature"}],"metadata":{"name":"Zela"},"type":"FeatureCollection"}