{"bbox":[35.3378,32.2874,35.368611,32.322222],"features":[{"geometry":{"coordinates":[35.368611,32.322222],"type":"Point"},"properties":{"id":"m4ff96d.point"},"type":"Feature"},{"geometry":{"coordinates":[35.337800,32.287400],"type":"Point"},"properties":{"id":"ma594e8.point"},"type":"Feature"}],"metadata":{"name":"Thebez"},"type":"FeatureCollection"}