{"bbox":[35.098819,31.541919,35.102252,31.566905],"features":[{"geometry":{"coordinates":[35.102252,31.566905],"type":"Point"},"properties":{"id":"m7454a1.point"},"type":"Feature"},{"geometry":{"coordinates":[35.098819,31.541919],"type":"Point"},"properties":{"id":"m9a6508.point"},"type":"Feature"}],"metadata":{"name":"Sirah"},"type":"FeatureCollection"}