{"bbox":[35.238992,31.798611,35.248333,31.831498],"features":[{"geometry":{"coordinates":[35.238992,31.805700],"type":"Point"},"properties":{"id":"m12013f.point"},"type":"Feature"},{"geometry":{"coordinates":[35.248333,31.798611],"type":"Point"},"properties":{"id":"m286edc.point"},"type":"Feature"},{"geometry":{"coordinates":[35.241283,31.831498],"type":"Point"},"properties":{"id":"m9f794c.point"},"type":"Feature"}],"metadata":{"name":"Laishah"},"type":"FeatureCollection"}