{"bbox":[35.07006,32.771772,35.155668,32.7988],"features":[{"geometry":{"coordinates":[35.070060,32.798800],"type":"Point"},"properties":{"id":"m52f985.point"},"type":"Feature"},{"geometry":{"coordinates":[35.155668,32.771772],"type":"Point"},"properties":{"id":"m52fd08.point"},"type":"Feature"}],"metadata":{"name":"Allammelech"},"type":"FeatureCollection"}