{"bbox":[35.23654,32.16857,36.733333,33.4],"features":[{"geometry":{"coordinates":[36.733333,32.666667],"type":"Point"},"properties":{"id":"m1dc3a0.point"},"type":"Feature"},{"geometry":{"coordinates":[35.355950,32.225980],"type":"Point"},"properties":{"id":"m4fc803.point"},"type":"Feature"},{"geometry":{"coordinates":[35.272778,32.199444],"type":"Point"},"properties":{"id":"m846c1f.point"},"type":"Feature"},{"geometry":{"coordinates":[35.273300,32.234000],"type":"Point"},"properties":{"id":"mc1032c.point"},"type":"Feature"},{"geometry":{"coordinates":[35.850000,33.400000],"type":"Point"},"properties":{"id":"mc78c4d.point"},"type":"Feature"},{"geometry":{"coordinates":[35.236540,32.168570],"type":"Point"},"properties":{"id":"mdea236.point"},"type":"Feature"}],"metadata":{"name":"Zalmon"},"type":"FeatureCollection"}