{"bbox":[34.86489,31.37124,34.86564,31.38333],"features":[{"geometry":{"coordinates":[34.864890,31.371240],"type":"Point"},"properties":{"id":"mee9587.point"},"type":"Feature"},{"geometry":{"coordinates":[34.865640,31.383330],"type":"Point"},"properties":{"id":"mfa3426.point"},"type":"Feature"}],"metadata":{"name":"En-rimmon"},"type":"FeatureCollection"}