{"bbox":[35.525833,32.766368,35.550553,32.806389],"features":[{"geometry":{"coordinates":[35.550553,32.766368],"type":"Point"},"properties":{"id":"m5b2a6f.point"},"type":"Feature"},{"geometry":{"coordinates":[35.525833,32.806389],"type":"Point"},"properties":{"id":"mfe591e.point"},"type":"Feature"}],"metadata":{"name":"Hammath 2"},"type":"FeatureCollection"}