{"bbox":[35.07006,32.67914,35.2414,32.7988],"features":[{"geometry":{"coordinates":[35.070060,32.798800],"type":"Point"},"properties":{"id":"m52f985.point"},"type":"Feature"},{"geometry":{"coordinates":[35.196950,32.679140],"type":"Point"},"properties":{"id":"m601c7a.point"},"type":"Feature"},{"geometry":{"coordinates":[35.241400,32.696700],"type":"Point"},"properties":{"id":"mc76c1b.point"},"type":"Feature"}],"metadata":{"name":"Nahalal"},"type":"FeatureCollection"}