{"bbox":[34.977712,31.43329,35.093592,31.55659],"features":[{"geometry":{"coordinates":[35.093592,31.549356],"type":"Point"},"properties":{"id":"m61740b.point"},"type":"Feature"},{"geometry":{"coordinates":[35.033550,31.556590],"type":"Point"},"properties":{"id":"m9dbf94.point"},"type":"Feature"},{"geometry":{"coordinates":[34.977712,31.433290],"type":"Point"},"properties":{"id":"me836d9.point"},"type":"Feature"}],"metadata":{"name":"Eshan"},"type":"FeatureCollection"}