{"bbox":[34.797404,31.080567,34.940812,31.36475],"features":[{"geometry":{"coordinates":[34.940812,31.080567],"type":"Point"},"properties":{"id":"m11f1d4.point"},"type":"Feature"},{"geometry":{"coordinates":[34.920610,31.364750],"type":"Point"},"properties":{"id":"m988bed.point"},"type":"Feature"},{"geometry":{"coordinates":[34.797404,31.281372],"type":"Point"},"properties":{"id":"mcfd3eb.point"},"type":"Feature"}],"metadata":{"name":"Iim"},"type":"FeatureCollection"}