{"bbox":[35.167744,32.486486,35.235272,32.501436],"features":[{"geometry":{"coordinates":[35.167744,32.501436],"type":"Point"},"properties":{"id":"md377f5.point"},"type":"Feature"},{"geometry":{"coordinates":[35.235272,32.486486],"type":"Point"},"properties":{"id":"mfde99e.point"},"type":"Feature"}],"metadata":{"name":"Janua"},"type":"FeatureCollection"}