{"bbox":[35.671878,31.777021,35.738498,31.819256],"features":[{"geometry":{"coordinates":[35.671878,31.819256],"type":"Point"},"properties":{"id":"m56a432.point"},"type":"Feature"},{"geometry":{"coordinates":[35.738498,31.777021],"type":"Point"},"properties":{"id":"m6b366e.point"},"type":"Feature"},{"geometry":{"coordinates":[35.722377,31.798459],"type":"Point"},"properties":{"id":"mcf60ee.point"},"type":"Feature"}],"metadata":{"name":"Beth-peor"},"type":"FeatureCollection"}