{"bbox":[34.746703,31.821483,34.812,31.823992],"features":[{"geometry":{"coordinates":[34.777744,31.822936],"type":"Point"},"properties":{"id":"m0af4d6.point"},"type":"Feature"},{"geometry":{"coordinates":[34.746703,31.823992],"type":"Point"},"properties":{"id":"m1b66b9.point"},"type":"Feature"},{"geometry":{"coordinates":[34.812000,31.821483],"type":"Point"},"properties":{"id":"m6129e7.point"},"type":"Feature"}],"metadata":{"name":"Shikkeron"},"type":"FeatureCollection"}