{"bbox":[35.665938,31.5753,35.68742,31.591311],"features":[{"geometry":{"coordinates":[35.665938,31.575300],"type":"Point"},"properties":{"id":"m9ce4af.point"},"type":"Feature"},{"geometry":{"coordinates":[35.687420,31.591311],"type":"Point"},"properties":{"id":"mbf104b.point"},"type":"Feature"}],"metadata":{"name":"Atroth-shophan"},"type":"FeatureCollection"}