{"bbox":[35.4175,32.749167,35.574903,32.94162],"features":[{"geometry":{"coordinates":[35.574903,32.941620],"type":"Point"},"properties":{"id":"m0c93b5.point"},"type":"Feature"},{"geometry":{"coordinates":[35.417500,32.931111],"type":"Point"},"properties":{"id":"m39107b.point"},"type":"Feature"},{"geometry":{"coordinates":[35.459722,32.799722],"type":"Point"},"properties":{"id":"m3d8db3.point"},"type":"Feature"},{"geometry":{"coordinates":[35.459167,32.749167],"type":"Point"},"properties":{"id":"m500952.point"},"type":"Feature"}],"metadata":{"name":"Adamah"},"type":"FeatureCollection"}