{"features":[{"geometry":{"coordinates":[35.180150,31.832733],"type":"Point"},"properties":{"id":"m17b4ff.point","role":"point"},"type":"Feature"}],"metadata":{"class":"human","land_or_water":"land","name":"Nabi Samwil","type":"settlement"},"type":"FeatureCollection"}