{"features":[{"geometry":{"coordinates":[35.094155,31.589383],"type":"Point"},"properties":{"id":"m1b2999.point","role":"point"},"type":"Feature"}],"metadata":{"class":"human","land_or_water":"land","name":"Khirbet et Tubeiqa","type":"settlement"},"type":"FeatureCollection"}