{"features":[{"geometry":{"coordinates":[35.245478,31.921866],"type":"Point"},"properties":{"geometry_credit":"osm","id":"m26f59b.point","role":"point"},"type":"Feature"}],"metadata":{"class":"human","land_or_water":"land","name":"Burj Beitin","type":"settlement"},"type":"FeatureCollection"}