{"features":[{"geometry":{"coordinates":[35.205790,31.816710],"type":"Point"},"properties":{"id":"m2adb90.point","role":"point"},"type":"Feature"}],"metadata":{"class":"human","land_or_water":"land","name":"Khirbet Tililiya","type":"settlement"},"type":"FeatureCollection"}