{"features":[{"geometry":{"coordinates":[35.750340,31.356569],"type":"Point"},"properties":{"id":"m328bf2.point","role":"point"},"type":"Feature"}],"metadata":{"class":"human","land_or_water":"land","name":"Dannea","type":"settlement"},"type":"FeatureCollection"}