{"features":[{"geometry":{"coordinates":[35.092000,31.959800],"type":"Point"},"properties":{"id":"m3f130c.point","role":"point"},"type":"Feature"}],"metadata":{"class":"human","land_or_water":"land","name":"Khirbet esh Shuna","type":"settlement"},"type":"FeatureCollection"}