{"features":[{"geometry":{"coordinates":[45.931389,33.123611],"type":"Point"},"properties":{"id":"m5bef14.point","role":"point"},"type":"Feature"}],"metadata":{"class":"human","land_or_water":"land","name":"Der","type":"settlement"},"type":"FeatureCollection"}