{"features":[{"geometry":{"coordinates":[35.306980,32.198360],"type":"Point"},"properties":{"id":"m62d2f9.point","role":"point"},"type":"Feature"}],"metadata":{"class":"human","land_or_water":"land","name":"Khirbet Ibn Naser","type":"settlement"},"type":"FeatureCollection"}