{"features":[{"geometry":{"coordinates":[35.560648,33.252728],"type":"Point"},"properties":{"id":"m6b2506.point","role":"point"},"type":"Feature"}],"metadata":{"class":"human","land_or_water":"land","name":"Khirbet Niha","type":"settlement"},"type":"FeatureCollection"}