{"features":[{"geometry":{"coordinates":[35.134350,32.734790],"type":"Point"},"properties":{"id":"m8b07e3.point","role":"point"},"type":"Feature"}],"metadata":{"class":"human","land_or_water":"land","name":"Khirbet Buseima","type":"settlement"},"type":"FeatureCollection"}