{"features":[{"geometry":{"coordinates":[35.230147,31.783957],"type":"Point"},"properties":{"id":"m9282d4.point","role":"point"},"type":"Feature"}],"metadata":{"class":"natural","land_or_water":"land","name":"Gordon’s Calvary","type":"hill"},"type":"FeatureCollection"}