{"features":[{"geometry":{"coordinates":[48.257780,32.189220],"type":"Point"},"properties":{"id":"m9cb1d4.point","role":"point"},"type":"Feature"}],"metadata":{"class":"human","land_or_water":"land","name":"Shush","type":"settlement"},"type":"FeatureCollection"}