{"features":[{"geometry":{"coordinates":[35.012365,31.687680],"type":"Point"},"properties":{"id":"ma31a83.point","role":"point"},"type":"Feature"}],"metadata":{"class":"human","land_or_water":"land","name":"Khirbet Beit Ika","type":"settlement"},"type":"FeatureCollection"}