{"features":[{"geometry":{"coordinates":[35.158731,31.601481],"type":"Point"},"properties":{"geometry_credit":"osm","id":"ma4d480.point","role":"point"},"type":"Feature"}],"metadata":{"class":"human","land_or_water":"land","name":"Khirbet ez Zawiya","type":"settlement"},"type":"FeatureCollection"}