{"features":[{"geometry":{"coordinates":[39.868306,29.811417],"type":"Point"},"properties":{"id":"ma4d11e.point","role":"point"},"type":"Feature"}],"metadata":{"class":"human","land_or_water":"land","name":"Dumat al Jandal","type":"settlement"},"type":"FeatureCollection"}