{"features":[{"geometry":{"coordinates":[35.399740,31.947200],"type":"Point"},"properties":{"id":"mc06f57.point","role":"point"},"type":"Feature"}],"metadata":{"class":"human","land_or_water":"land","name":"Khirbet el Aujah el Foqa","type":"settlement"},"type":"FeatureCollection"}