{"features":[{"geometry":{"coordinates":[35.228036,31.776083],"type":"Point"},"properties":{"id":"mecccdd.point","role":"point"},"type":"Feature"}],"metadata":{"class":"human","land_or_water":"land","name":"Herod’s palace in Jerusalem","type":"structure"},"type":"FeatureCollection"}