{"features":[{"geometry":{"coordinates":[35.397360,32.368840],"type":"Point"},"properties":{"id":"mf2c1fd.point","role":"point"},"type":"Feature"}],"metadata":{"class":"human","land_or_water":"land","name":"Khirbet Ibziq","type":"settlement"},"type":"FeatureCollection"}